odoo/addons/ssi_service/README.rst
odoo/addons/ssi_service/__init__.py
odoo/addons/ssi_service/__manifest__.py
odoo/addons/ssi_service/menu.xml
odoo/addons/ssi_service/data/approval_template_data.xml
odoo/addons/ssi_service/data/ir_sequence_data.xml
odoo/addons/ssi_service/data/policy_template_data.xml
odoo/addons/ssi_service/data/sequence_template_data.xml
odoo/addons/ssi_service/models/__init__.py
odoo/addons/ssi_service/models/res_company.py
odoo/addons/ssi_service/models/res_config_settings.py
odoo/addons/ssi_service/models/service_contract.py
odoo/addons/ssi_service/models/service_contract_fix_item.py
odoo/addons/ssi_service/models/service_contract_fix_item_payment_term.py
odoo/addons/ssi_service/models/service_contract_fix_item_payment_term_detail.py
odoo/addons/ssi_service/models/service_fix_item_mixin.py
odoo/addons/ssi_service/models/service_fix_item_payment_term_detail_mixin.py
odoo/addons/ssi_service/models/service_fix_item_payment_term_mixin.py
odoo/addons/ssi_service/models/service_mixin.py
odoo/addons/ssi_service/models/service_type.py
odoo/addons/ssi_service/security/ir.model.access.csv
odoo/addons/ssi_service/security/ir_module_category_data.xml
odoo/addons/ssi_service/security/ir_rule_data.xml
odoo/addons/ssi_service/security/res_group_data.xml
odoo/addons/ssi_service/static/description/icon.png
odoo/addons/ssi_service/views/res_config_settings_views.xml
odoo/addons/ssi_service/views/service_contract_fix_item_payment_term_views.xml
odoo/addons/ssi_service/views/service_contract_views.xml
odoo/addons/ssi_service/views/service_type_views.xml
odoo/addons/ssi_service/wizards/__init__.py
odoo/addons/ssi_service/wizards/link_invoice_to_payment_term.py
odoo/addons/ssi_service/wizards/link_invoice_to_payment_term.xml
odoo14_addon_ssi_service-14.0.2.9.0.dist-info/METADATA
odoo14_addon_ssi_service-14.0.2.9.0.dist-info/WHEEL
odoo14_addon_ssi_service-14.0.2.9.0.dist-info/top_level.txt
odoo14_addon_ssi_service-14.0.2.9.0.dist-info/RECORD
