Metadata-Version: 2.1
Name: odoo14-addon-ssi_service
Version: 14.0.2.9.0
Summary: Service
Home-page: https://simetri-sinergi.id
Author: OpenSynergy Indonesia, PT. Simetri Sinergi Indonesia
License: AGPL-3
Classifier: Programming Language :: Python
Classifier: Framework :: Odoo
Classifier: Framework :: Odoo :: 14.0
Classifier: License :: OSI Approved :: GNU Affero General Public License v3
Requires-Python: >=3.6
Requires-Dist: odoo14-addon-ssi-cost-accounting
Requires-Dist: odoo14-addon-ssi-duration-mixin
Requires-Dist: odoo14-addon-ssi-master-data-mixin
Requires-Dist: odoo14-addon-ssi-partner-mixin
Requires-Dist: odoo14-addon-ssi-product-line-account-mixin
Requires-Dist: odoo14-addon-ssi-source-document-mixin
Requires-Dist: odoo14-addon-ssi-transaction-cancel-mixin
Requires-Dist: odoo14-addon-ssi-transaction-confirm-mixin
Requires-Dist: odoo14-addon-ssi-transaction-done-mixin
Requires-Dist: odoo14-addon-ssi-transaction-open-mixin
Requires-Dist: odoo14-addon-ssi-transaction-pricelist-mixin
Requires-Dist: odoo14-addon-ssi-transaction-salesperson-mixin
Requires-Dist: odoo14-addon-ssi-transaction-terminate-mixin
Requires-Dist: odoo<14.1dev,>=14.0a
